gjdatac_api/__init__.py
gjdatac_api/data_api_class.py
gjdatac_api/dict_data.py
gjdatac_api/dolphindb_info.py
gjdatac_api/instrument_class.py
gjdatac_api-0.3.3.dist-info/METADATA
gjdatac_api-0.3.3.dist-info/WHEEL
gjdatac_api-0.3.3.dist-info/top_level.txt
gjdatac_api-0.3.3.dist-info/RECORD
