Metadata-Version: 2.4
Name: gjdatac_api
Version: 0.3.3
Summary: 数据接口打包
Author: fml
Author-email: 13306510996@163.com
Requires-Python: >3.6
Requires-Dist: dolphindb==3.0.1.0
Requires-Dist: holidays==0.53
Requires-Dist: numpy==1.26.3
Requires-Dist: pandas==2.2.0
Requires-Dist: chinese_calendar==1.10.0
Dynamic: author
Dynamic: author-email
Dynamic: description
Dynamic: description-content-type
Dynamic: requires-dist
Dynamic: requires-python
Dynamic: summary
